{
  "project_info": {
    "project_number": "343723762122",
    "project_id": "albumfilmesapp",
    "storage_bucket": "albumfilmesapp.firebasestorage.app"
  },
  "client": [
    {
      "client_info": {
        "mobilesdk_app_id": "1:343723762122:android:db2d794e2b534c45e86f33",
        "android_client_info": {
          "package_name": "com.example.album_filmes_app"
        }
      },
      "oauth_client": [],
      "api_key": [
        {
          "current_key": "AIzaSyD8VQ-DaypzshHpBzMuQqfIBbnhxBHEbwk"
        }
      ],
      "services": {
        "appinvite_service": {
          "other_platform_oauth_client": []
        }
      }
    }
  ],
  "configuration_version": "1"
}